MANIFEST.in
README
requirements.txt
setup.py
jawbone/__init__.py
jawbone/jawbone.py
jawbone_up.egg-info/PKG-INFO
jawbone_up.egg-info/SOURCES.txt
jawbone_up.egg-info/dependency_links.txt
jawbone_up.egg-info/not-zip-safe
jawbone_up.egg-info/requires.txt
jawbone_up.egg-info/top_level.txt