Metadata-Version: 1.0
Name: jawbone-up
Version: 0.1
Summary: Jawbone UP API python wrapper
Home-page: https://github.com/karthikbgl/python-jawbone-up
Author: Karthik Ravindra
Author-email: karthikbgl@gmail.com
License: UNKNOWN
Platform: UNKNOWN
